kombu/__init__.py
kombu/abstract.py
kombu/clocks.py
kombu/common.py
kombu/compat.py
kombu/compression.py
kombu/connection.py
kombu/entity.py
kombu/exceptions.py
kombu/log.py
kombu/matcher.py
kombu/message.py
kombu/messaging.py
kombu/mixins.py
kombu/pidbox.py
kombu/pools.py
kombu/resource.py
kombu/serialization.py
kombu/simple.py
kombu/asynchronous/__init__.py
kombu/asynchronous/debug.py
kombu/asynchronous/hub.py
kombu/asynchronous/semaphore.py
kombu/asynchronous/timer.py
kombu/asynchronous/aws/__init__.py
kombu/asynchronous/aws/connection.py
kombu/asynchronous/aws/ext.py
kombu/asynchronous/aws/sqs/__init__.py
kombu/asynchronous/aws/sqs/connection.py
kombu/asynchronous/aws/sqs/ext.py
kombu/asynchronous/aws/sqs/message.py
kombu/asynchronous/aws/sqs/queue.py
kombu/asynchronous/http/__init__.py
kombu/asynchronous/http/base.py
kombu/asynchronous/http/curl.py
kombu/transport/SLMQ.py
kombu/transport/SQS.py
kombu/transport/__init__.py
kombu/transport/azureservicebus.py
kombu/transport/azurestoragequeues.py
kombu/transport/base.py
kombu/transport/confluentkafka.py
kombu/transport/consul.py
kombu/transport/etcd.py
kombu/transport/filesystem.py
kombu/transport/gcpubsub.py
kombu/transport/librabbitmq.py
kombu/transport/memory.py
kombu/transport/mongodb.py
kombu/transport/native_delayed_delivery.py
kombu/transport/pyamqp.py
kombu/transport/pyro.py
kombu/transport/qpid.py
kombu/transport/redis.py
kombu/transport/zookeeper.py
kombu/transport/sqlalchemy/__init__.py
kombu/transport/sqlalchemy/models.py
kombu/transport/virtual/__init__.py
kombu/transport/virtual/base.py
kombu/transport/virtual/exchange.py
kombu/utils/__init__.py
kombu/utils/amq_manager.py
kombu/utils/collections.py
kombu/utils/compat.py
kombu/utils/debug.py
kombu/utils/div.py
kombu/utils/encoding.py
kombu/utils/eventio.py
kombu/utils/functional.py
kombu/utils/imports.py
kombu/utils/json.py
kombu/utils/limits.py
kombu/utils/objects.py
kombu/utils/scheduling.py
kombu/utils/text.py
kombu/utils/time.py
kombu_asyncio-6.0.0a1.dist-info/licenses/LICENSE
kombu_asyncio-6.0.0a1.dist-info/METADATA
kombu_asyncio-6.0.0a1.dist-info/WHEEL
kombu_asyncio-6.0.0a1.dist-info/top_level.txt
kombu_asyncio-6.0.0a1.dist-info/RECORD
